datesort/__init__.py
datesort/plugin.py
paginate/__init__.py
paginate/plugin.py
rebalance/__init__.py
rebalance/base.html
rebalance/card.html
rebalance/footer.html
rebalance/head.html
rebalance/header.html
rebalance/home.html
rebalance/main.html
rebalance/mkdocs_theme.yml
rebalance/post.html
rebalance/search-modal.html
rebalance/search.html
rebalance/social.html
rebalance/style.css
rebalance/font-awesome/font-awesome.css
rebalance/font-awesome/fontawesome-webfont.eot
rebalance/font-awesome/fontawesome-webfont.svg
rebalance/font-awesome/fontawesome-webfont.ttf
rebalance/font-awesome/fontawesome-webfont.woff
rebalance/font-awesome/fontawesome-webfont.woff2
rebalance/js/base.js
mkdocs_rebalance_theme-0.0.21.dist-info/METADATA
mkdocs_rebalance_theme-0.0.21.dist-info/WHEEL
mkdocs_rebalance_theme-0.0.21.dist-info/entry_points.txt
mkdocs_rebalance_theme-0.0.21.dist-info/top_level.txt
mkdocs_rebalance_theme-0.0.21.dist-info/RECORD
