Metadata-Version: 2.1
Name: mkdocs-rebalance-theme
Version: 0.0.21
Summary: Rebalance theme for mkdocs
Home-page: https://github.com/kubilus1/mkdocs-rebalance-theme
Author: Matt Kubilus
Author-email: mattkubilus@gmail.com
License: GPL
Platform: UNKNOWN
Requires-Dist: mkdocs-datesort-plugin (>=0.0.2)
Requires-Dist: mkdocs-paginate-plugin (>=0.0.6)
Requires-Dist: mkdocs (>=0.17)
